ipython_utils/__init__.py
ipython_utils/__main__.py
ipython_utils/core.py
ipython_utils-1.1.6.dist-info/METADATA
ipython_utils-1.1.6.dist-info/WHEEL
ipython_utils-1.1.6.dist-info/licenses/LICENSE
ipython_utils-1.1.6.dist-info/licenses/NOTICE
ipython_utils-1.1.6.dist-info/RECORD
