Metadata-Version: 2.4
Name: ipython_utils
Version: 1.1.6
Summary: Utilities to make developing Python responsive and interactive using fully powered shells directly embedded at the target location or exception site, or dynamically reloading updated code
Project-URL: Homepage, https://github.com/limwz01/ipython_utils
Project-URL: Issues, https://github.com/limwz01/ipython_utils/issues
Author-email: limwz01 <117669574+limwz01@users.noreply.github.com>
License-File: LICENSE
License-File: NOTICE
Classifier: License :: OSI Approved :: MIT License
Classifier: Operating System :: OS Independent
Classifier: Programming Language :: Python :: 3
Requires-Python: >=3.8
Requires-Dist: ipython>=8.10.0
